README.rst
setup.py
xontrib/rerun.xsh
xontrib/test_xontrib_rerun.py
xontrib_rerun.egg-info/PKG-INFO
xontrib_rerun.egg-info/SOURCES.txt
xontrib_rerun.egg-info/dependency_links.txt
xontrib_rerun.egg-info/requires.txt
xontrib_rerun.egg-info/top_level.txt