Metadata-Version: 1.1
Name: xontrib-rerun
Version: 0.8
Summary: Rerun previous commands
Home-page: https://github.com/kmarilleau/xontrib-rerun
Author: Kevin Marilleau
Author-email: kevin.marilleau@gmail.com
License: GPLv3+
Platform: any
Classifier: Environment :: Console
Classifier: Environment :: Plugins
Classifier: Topic :: System :: Shells
Classifier: Topic :: System :: System Shells
Classifier: Development Status :: 3 - Alpha
Classifier: License :: OSI Approved :: GNU General Public License v3 or later (GPLv3+)
Classifier: Programming Language :: Python :: 3
Classifier: Programming Language :: Python :: 3.7
